drift/__init__.py
drift/version.py
drift/core/__init__.py
drift/core/batch_processor.py
drift/core/config.py
drift/core/content_type_utils.py
drift/core/data_normalization.py
drift/core/drift_sdk.py
drift/core/json_schema_helper.py
drift/core/logger.py
drift/core/metrics.py
drift/core/mock_utils.py
drift/core/mode_utils.py
drift/core/resilience.py
drift/core/sampling.py
drift/core/span_serialization.py
drift/core/trace_blocking_manager.py
drift/core/types.py
drift/core/communication/__init__.py
drift/core/communication/communicator.py
drift/core/communication/types.py
drift/core/tracing/__init__.py
drift/core/tracing/otel_converter.py
drift/core/tracing/span_exporter.py
drift/core/tracing/span_utils.py
drift/core/tracing/td_attributes.py
drift/core/tracing/td_span_processor.py
drift/core/tracing/adapters/__init__.py
drift/core/tracing/adapters/api.py
drift/core/tracing/adapters/base.py
drift/core/tracing/adapters/filesystem.py
drift/core/tracing/adapters/memory.py
drift/instrumentation/__init__.py
drift/instrumentation/base.py
drift/instrumentation/registry.py
drift/instrumentation/aiohttp/__init__.py
drift/instrumentation/aiohttp/instrumentation.py
drift/instrumentation/aiohttp/e2e-tests/entrypoint.py
drift/instrumentation/aiohttp/e2e-tests/src/app.py
drift/instrumentation/aiohttp/e2e-tests/src/test_requests.py
drift/instrumentation/datetime/__init__.py
drift/instrumentation/datetime/instrumentation.py
drift/instrumentation/django/__init__.py
drift/instrumentation/django/instrumentation.py
drift/instrumentation/django/middleware.py
drift/instrumentation/django/e2e-tests/entrypoint.py
drift/instrumentation/django/e2e-tests/src/app.py
drift/instrumentation/django/e2e-tests/src/settings.py
drift/instrumentation/django/e2e-tests/src/test_requests.py
drift/instrumentation/django/e2e-tests/src/urls.py
drift/instrumentation/django/e2e-tests/src/views.py
drift/instrumentation/e2e_common/__init__.py
drift/instrumentation/e2e_common/base_runner.py
tusk_drift_python_sdk-0.1.13.dist-info/licenses/LICENSE
tusk_drift_python_sdk-0.1.13.dist-info/METADATA
tusk_drift_python_sdk-0.1.13.dist-info/WHEEL
tusk_drift_python_sdk-0.1.13.dist-info/top_level.txt
tusk_drift_python_sdk-0.1.13.dist-info/RECORD
