Metadata-Version: 2.4
Name: tusk-drift-python-sdk
Version: 0.1.13
Summary: Python SDK for Tusk Drift instrumentation and replay
Author-email: Tusk <support@usetusk.ai>
License: Apache-2.0
Project-URL: Homepage, https://usetusk.ai
Project-URL: Documentation, https://docs.usetusk.ai
Project-URL: Repository, https://github.com/Use-Tusk/drift-python-sdk
Project-URL: Issues, https://github.com/Use-Tusk/drift-python-sdk/issues
Keywords: tusk,drift,testing,instrumentation,tracing,replay
Classifier: Development Status :: 3 - Alpha
Classifier: Intended Audience :: Developers
Classifier: License :: OSI Approved :: Apache Software License
Classifier: Programming Language :: Python :: 3
Classifier: Programming Language :: Python :: 3.9
Classifier: Programming Language :: Python :: 3.10
Classifier: Programming Language :: Python :: 3.11
Classifier: Programming Language :: Python :: 3.12
Classifier: Programming Language :: Python :: 3.13
Classifier: Topic :: Software Development :: Testing
Classifier: Topic :: Software Development :: Libraries :: Python Modules
Requires-Python: >=3.9
License-File: LICENSE
Requires-Dist: protobuf>=6.0
Requires-Dist: PyYAML>=6.0
Requires-Dist: requests>=2.32.5
Requires-Dist: tusk-drift-schemas>=0.1.24
Requires-Dist: aiohttp>=3.9.0
Requires-Dist: aiofiles>=23.0.0
Requires-Dist: opentelemetry-api>=1.20.0
Requires-Dist: opentelemetry-sdk>=1.20.0
Requires-Dist: time-machine>=2.10.0
Requires-Dist: typing_extensions>=4.4.0
Provides-Extra: flask
Requires-Dist: Flask>=3.1.2; extra == "flask"
Provides-Extra: fastapi
Requires-Dist: fastapi>=0.115.6; extra == "fastapi"
Requires-Dist: uvicorn>=0.34.2; extra == "fastapi"
Requires-Dist: starlette<0.42.0; extra == "fastapi"
Provides-Extra: django
Requires-Dist: Django>=4.2; extra == "django"
Provides-Extra: dev
Requires-Dist: Flask>=3.1.2; extra == "dev"
Requires-Dist: fastapi>=0.115.6; extra == "dev"
Requires-Dist: uvicorn>=0.34.2; extra == "dev"
Requires-Dist: python-jsonpath>=0.10; extra == "dev"
Requires-Dist: ruff>=0.8.0; extra == "dev"
Requires-Dist: ty>=0.0.1a7; extra == "dev"
Requires-Dist: pytest<9.0.0,>=8.0.0; extra == "dev"
Requires-Dist: pytest-mock>=3.15.0; extra == "dev"
Requires-Dist: pytest-cov>=7.0.0; extra == "dev"
Dynamic: license-file
